geoservice/__init__.py
geoservice/__main__.py
geoservice/dao/__init__.py
geoservice/models/__init__.py
geoservice/models/ip_geolocation.py
geoservice/parsers/__init__.py
geoservice/parsers/reader.py
geoservice-0.0.1.dist-info/DESCRIPTION.rst
geoservice-0.0.1.dist-info/METADATA
geoservice-0.0.1.dist-info/RECORD
geoservice-0.0.1.dist-info/WHEEL
geoservice-0.0.1.dist-info/metadata.json
geoservice-0.0.1.dist-info/top_level.txt
