Metadata-Version: 2.0
Name: geoservice
Version: 0.0.1
Summary: CSV Parser for IP Geolocation data
Home-page: http://github.com/rayattack/geoservice
Author: Raymond Ortserga
Author-email: ortserga@yahoo.com
License: MIT
Keywords: CSV Parser IP Location
Platform: UNKNOWN
Classifier: Development Status :: 3 - Alpha
Classifier: Programming Language :: Python :: 2.6
Classifier: Programming Language :: Python :: 2.7
Classifier: Programming Language :: Python :: Implementation :: CPython
Classifier: Topic :: Utilities
Classifier: Topic :: Software Development
Requires-Dist: mongoengine
